gimmebio.stat_strains-0.4.5-py3.6-nspkg.pth
gimmebio/stat_strains/__init__.py
gimmebio/stat_strains/api.py
gimmebio/stat_strains/cli.py
gimmebio/stat_strains/metrics.py
gimmebio.stat_strains-0.4.5.dist-info/METADATA
gimmebio.stat_strains-0.4.5.dist-info/WHEEL
gimmebio.stat_strains-0.4.5.dist-info/namespace_packages.txt
gimmebio.stat_strains-0.4.5.dist-info/top_level.txt
gimmebio.stat_strains-0.4.5.dist-info/RECORD
